daqua/__init__.py
daqua/config.py
daqua/descriptive_util.py
daqua/main.py
daqua/read_flat_file.py
daqua/read_from_db.py
daqua/stats_util.py
daqua-0.0.1.1.dist-info/LICENSE
daqua-0.0.1.1.dist-info/METADATA
daqua-0.0.1.1.dist-info/WHEEL
daqua-0.0.1.1.dist-info/entry_points.txt
daqua-0.0.1.1.dist-info/top_level.txt
daqua-0.0.1.1.dist-info/RECORD
